dictManipulate
