Metadata-Version: 1.0
Name: dictManipulate
Version: 0.6
Summary: data_manipulate
Home-page: UNKNOWN
Author: UNKNOWN
Author-email: UNKNOWN
License: UNKNOWN
Platform: UNKNOWN
